workday_mcp/__init__.py
workday_mcp/__main__.py
workday_mcp/server.py
test_workday_mcpserver_py-0.1.1.dist-info/METADATA
test_workday_mcpserver_py-0.1.1.dist-info/WHEEL
test_workday_mcpserver_py-0.1.1.dist-info/entry_points.txt
test_workday_mcpserver_py-0.1.1.dist-info/top_level.txt
test_workday_mcpserver_py-0.1.1.dist-info/RECORD
