Metadata-Version: 2.4
Name: test-workday-mcpserver-py
Version: 0.1.1
Summary: WORKDAY is an HRMS
Author-email: Workday MCP <nandisha.d@think41.com>
Requires-Python: >=3.12
Requires-Dist: mcp[cli]>=1.6.0
Requires-Dist: requests>=2.32.3
Requires-Dist: twine>=6.1.0
Requires-Dist: python-dotenv>=1.0.0
